{"css_textcontrol.md":"566f4430","html_formsandlists.md":"10dd5bff","html_index.md":"c4eac6a7","html_picturesandlinks.md":"68bbd5cf","html_tablemultimedia.md":"6bd862a7","typescriptmd_decorator.md":"7801ac66","typescriptmd_dispose.md":"1a7d2c1e","typescriptmd_typetool.md":"79c65413","css_selector.md":"6fd5569c","index.md":"4bea5a60","javascript_index.md":"4d6ae142","learningnotes_index.md":"65b6f682","typescriptmd_foundationtype.md":"4f85cfd7","css_boxmodel.md":"dc8d16e5","css_datastyle.md":"d038e0e1","css_elementweight.md":"b7a57089","typescriptmd_index.md":"d4366c87","javascript_basicdata.md":"828d1f61","html_text.md":"dca797d8","css_flex.md":"69b3eab8","css_float.md":"9ac7bd13","typescriptmd_genericparadigm.md":"794dfb73","learningnotes_html.md":"ba512d3d","typescriptmd_tsmodule.md":"ca6cdc97","css_positions.md":"d388694d","css_backgroundprocessing.md":"91902da8","typescriptmd_class.md":"a715e60f","javascript_processcontrol.md":"3a2b299f","nav_index.md":"5892b5af","typescriptmd_certainty.md":"1986489d","css_index.md":"306b51d0"}
